mytest_multiply/__init__.py
mytest_multiply/multiplication.py
mytest_multiply-0.1.0.dist-info/METADATA
mytest_multiply-0.1.0.dist-info/WHEEL
mytest_multiply-0.1.0.dist-info/top_level.txt
mytest_multiply-0.1.0.dist-info/RECORD
